dopameme/__init__.py
dopameme/constants.py
dopameme/cute.py
dopameme/entry_point.py
dopameme/search.py
dopameme/testlib.py
dopameme/backends/__init__.py
dopameme/backends/base.py
dopameme/backends/yandex.py
dopameme-0.2.0.dist-info/LICENSE
dopameme-0.2.0.dist-info/METADATA
dopameme-0.2.0.dist-info/WHEEL
dopameme-0.2.0.dist-info/entry_points.txt
dopameme-0.2.0.dist-info/top_level.txt
dopameme-0.2.0.dist-info/RECORD
