Metadata-Version: 2.1
Name: dopameme
Version: 0.2.0
Summary: Get a quick dopamine hit of cuteness
Home-page: UNKNOWN
License: UNKNOWN
Keywords: cute,adorable,dopamine
Platform: UNKNOWN
Classifier: Intended Audience :: End Users/Desktop
Classifier: Operating System :: OS Independent
Classifier: Programming Language :: Python
Classifier: Programming Language :: Python :: 3.6
Classifier: Programming Language :: Python :: 3.7
Classifier: Programming Language :: Python :: 3.8
Classifier: Programming Language :: Python :: 3.9
Classifier: Programming Language :: Python :: 3.10
Classifier: Topic :: Internet :: WWW/HTTP :: Dynamic Content
Requires-Python: >=3.6
License-File: LICENSE
Requires-Dist: requests
Requires-Dist: log-color
Requires-Dist: lxml
Provides-Extra: dev
Requires-Dist: black ; extra == 'dev'
Requires-Dist: setuptools-scm ; extra == 'dev'
